Dividers/__init__.py
Dividers/div.py
Dividers-0.0.3.dist-info/LICENSE
Dividers-0.0.3.dist-info/METADATA
Dividers-0.0.3.dist-info/WHEEL
Dividers-0.0.3.dist-info/top_level.txt
Dividers-0.0.3.dist-info/RECORD
