Metadata-Version: 2.1
Name: Dividers
Version: 0.0.3
Summary: Creating dividers (divs) for CLI or output files
Author: Burritoless Codec
Keywords: python,dividers,cli,output
License-File: LICENSE
